SCPSyncer/__init__.py
SCPSyncer/__main__.py
SCPSyncer/remote_hasher.py
SCPSyncer/scp_syncer.py
SCPSyncer-0.1.dist-info/LICENSE
SCPSyncer-0.1.dist-info/METADATA
SCPSyncer-0.1.dist-info/WHEEL
SCPSyncer-0.1.dist-info/top_level.txt
SCPSyncer-0.1.dist-info/RECORD
