Metadata-Version: 2.1
Name: SCPSyncer
Version: 0.1
Summary: SCP syncer
Home-page: https://github.com/Frederic98/SCP-Syncer
Author: Frederic98
License: UNKNOWN
Keywords: scp sync syncer
Platform: UNKNOWN
Requires-Dist: paramiko
Requires-Dist: scp
Requires-Dist: PyYAML
Requires-Dist: colorama
